django_leek/__init__.py
django_leek/api.py
django_leek/cloud_logging.py
django_leek/helpers.py
django_leek/models.py
django_leek/server.py
django_leek/service-stop-worker.py
django_leek/settings.py
django_leek/tests.py
django_leek/management/__init__.py
django_leek/management/commands/__init__.py
django_leek/management/commands/leek.py
django_leek/migrations/0001_initial.py
django_leek/migrations/0002_queuedtasks_pool.py
django_leek/migrations/0003_auto_20180910_1028.py
django_leek/migrations/0004_new_task_structure_20200310_1518.py
django_leek/migrations/__init__.py
test_app/migrations/0001_initial.py
test_app/migrations/__init__.py
django_leek-1.0.7.dist-info/LICENSE
django_leek-1.0.7.dist-info/METADATA
django_leek-1.0.7.dist-info/WHEEL
django_leek-1.0.7.dist-info/top_level.txt
django_leek-1.0.7.dist-info/RECORD
