Metadata-Version: 2.1
Name: django-leek
Version: 1.0.7
Summary: A simple Django app to offload tasks from main web server
Home-page: https://github.com/Volumental/django-leek
Author: Volumental
Author-email: maintainer@volumental.com
License: MIT License
Platform: UNKNOWN
Classifier: Environment :: Web Environment
Classifier: Framework :: Django
Classifier: Framework :: Django :: 3.2
Classifier: Intended Audience :: Developers
Classifier: Operating System :: OS Independent
Classifier: Programming Language :: Python
Classifier: Programming Language :: Python :: 3.6
Classifier: Programming Language :: Python :: 3.10
Classifier: Topic :: Internet :: WWW/HTTP
Classifier: Topic :: Internet :: WWW/HTTP :: Dynamic Content
License-File: LICENSE
Requires-Dist: django>=3.2
Requires-Dist: google-cloud-logging>=3.0.0
